kernels/__init__.py
kernels/_system.py
kernels/_versions.py
kernels/_windows.py
kernels/benchmark.py
kernels/check.py
kernels/cli.py
kernels/compat.py
kernels/deps.py
kernels/doc.py
kernels/lockfile.py
kernels/metadata.py
kernels/python_depends.json
kernels/upload.py
kernels/utils.py
kernels/variants.py
kernels/versions_cli.py
kernels/_vendored/convert_rst_to_mdx.py
kernels/benchmarks/__init__.py
kernels/benchmarks/activation.py
kernels/benchmarks/attention.py
kernels/benchmarks/layer_norm.py
kernels/layer/__init__.py
kernels/layer/_interval_tree.py
kernels/layer/device.py
kernels/layer/func.py
kernels/layer/globals.py
kernels/layer/kernelize.py
kernels/layer/layer.py
kernels/layer/mode.py
kernels/layer/repos.py
kernels-0.12.1.dist-info/METADATA
kernels-0.12.1.dist-info/WHEEL
kernels-0.12.1.dist-info/entry_points.txt
kernels-0.12.1.dist-info/top_level.txt
kernels-0.12.1.dist-info/RECORD
