Metadata-Version: 2.4
Name: kernels
Version: 0.12.1
Summary: Download compute kernels
Author-email: OlivierDehaene <olivier@huggingface.co>, Daniel de Kok <daniel@huggingface.co>, David Holtz <david@huggingface.co>, Nicolas Patry <nicolas@huggingface.co>
License: Apache-2.0
Requires-Python: >=3.9
Requires-Dist: huggingface_hub<2.0,>=0.26.0
Requires-Dist: packaging>=20.0
Requires-Dist: pyyaml>=6
Requires-Dist: tomli>=2.0; python_version < "3.11"
Provides-Extra: abi-check
Requires-Dist: kernel-abi-check<0.7.0,>=0.6.2; extra == "abi-check"
Provides-Extra: benchmark
Requires-Dist: numpy>=2.0.2; extra == "benchmark"
Requires-Dist: requests>=2.32.5; extra == "benchmark"
Requires-Dist: torch; extra == "benchmark"
Provides-Extra: torch
Requires-Dist: torch; extra == "torch"
Provides-Extra: docs
Requires-Dist: hf-doc-builder; extra == "docs"
